{
  "api_name": "wmds_fundQuoteSummary",
  "product_code": "U62345",
  "timestamp": "20250813_212612",
  "total_responses": 1,
  "responses": [
    {
      "timestamp": "2025-08-13T21:46:30.000110",
      "url": "https://investments3.personal-banking.hsbc.com.hk/shp/wealth-mobile-mds-shp-api-hk-hbap-prod-proxy/v0/wmds/fundQuoteSummary?body=%7B%22productType%22%3A%22UT%22%2C%22prodAltNum%22%3A%22U62345%22%2C%22prodCdeAltClassCde%22%3A%22M%22%2C%22market%22%3A%22HK%22%7D",
      "status": 200,
      "status_text": "",
      "headers": {
        "x-request-id": "d5ed721c-e341-4b92-8088-06a65cb82d81:-:-:-",
        "access-control-expose-headers": "x-authtoken",
        "ratelimit-remaining": "16",
        "content-encoding": "gzip",
        "ratelimit-reset": "1",
        "x-content-type-options": "nosniff",
        "x-ratelimit-limit-second": "20",
        "expires": "0",
        "x-cache": "Miss from cloudfront",
        "x-amz-cf-id": "6b_kgW9sgkFeIKUxsdeNt7xy2ohMVx0bLtc6D1dEwq8_xV6IU_RAOw==",
        "x-hsbc-request-correlation-id": "8c2fb4a2-94ab-47d9-acc4-8930c48009a5",
        "date": "Wed, 13 Aug 2025 13:46:29 GMT",
        "content-type": "application/json;charset=UTF-8",
        "vary": "Accept-Encoding",
        "x-frame-options": "SAMEORIGIN, DENY",
        "strict-transport-security": "max-age=31536000; includeSubDomains",
        "content-security-policy": "default-src 'self';",
        "cache-control": "no-cache, no-store, max-age=0, must-revalidate, no-store, no-cache, must-revalidate",
        "s": "rproxy_prod_tko_0255",
        "pragma": "no-cache, no-cache",
        "x-ratelimit-remaining-second": "16",
        "x-envoy-upstream-service-time": "30",
        "ratelimit-limit": "20",
        "referrer-policy": "no-referrer",
        "via": "1.1 619e9f7b6fc5db300230b5cfc11ec0ca.cloudfront.net (CloudFront)",
        "access-control-allow-credentials": "true",
        "content-length": "2927",
        "x-xss-protection": "1 ; mode=block",
        "x-amz-cf-pop": "LAX54-P4"
      },
      "content_type": "application/json;charset=UTF-8",
      "response_body": "{\"summary\":{\"bid\":null,\"weekRangeLow\":39.75000,\"weekRangeHigh\":52.10000,\"offer\":null,\"weekRangeCurrency\":\"USD\",\"calendarYearTotalReturns\":{\"items\":[{\"year\":2024,\"fundCalendarYearReturn\":1.77951,\"fundStubYearEndReturn\":null,\"stubYearEndReturnIndicator\":null,\"bestFitIndexCalendarYearReturn\":12.95445,\"categoryCalendarYearReturn\":3.80173,\"prospectusPrimaryIndexYearReturns\":null},{\"year\":2023,\"fundCalendarYearReturn\":-5.21520,\"fundStubYearEndReturn\":null,\"stubYearEndReturnIndicator\":null,\"bestFitIndexCalendarYearReturn\":16.75059,\"categoryCalendarYearReturn\":-1.12415,\"prospectusPrimaryIndexYearReturns\":null},{\"year\":2022,\"fundCalendarYearReturn\":9.81478,\"fundStubYearEndReturn\":null,\"stubYearEndReturnIndicator\":null,\"bestFitIndexCalendarYearReturn\":-15.32062,\"categoryCalendarYearReturn\":14.30746,\"prospectusPrimaryIndexYearReturns\":null},{\"year\":2021,\"fundCalendarYearReturn\":3.43537,\"fundStubYearEndReturn\":null,\"stubYearEndReturnIndicator\":null,\"bestFitIndexCalendarYearReturn\":12.36960,\"categoryCalendarYearReturn\":0.78903,\"prospectusPrimaryIndexYearReturns\":null},{\"year\":2020,\"fundCalendarYearReturn\":6.99811,\"fundStubYearEndReturn\":null,\"stubYearEndReturnIndicator\":null,\"bestFitIndexCalendarYearReturn\":14.26179,\"categoryCalendarYearReturn\":2.81511,\"prospectusPrimaryIndexYearReturns\":null}],\"bestFitIndex\":\"Morningstar US Mod Tgt Alloc NR USD\",\"lastUpdatedDate\":\"2025-07-31\",\"dailyLastUpdatedDate\":\"2025-08-11\"},\"cumulativeTotalReturns\":{\"items\":[{\"period\":\"YTD\",\"totalReturn\":-15.81592,\"totalDailyReturn\":-14.06752,\"bestFitIndexReturn\":-0.06506,\"categoryReturn\":-7.15753,\"categoryDailyReturn\":-1.40189,\"primaryIndexReturn\":7.71730,\"prospectusPrimaryIndexReturns\":null},{\"period\":\"1M\",\"totalReturn\":-1.52797,\"totalDailyReturn\":0.42273,\"bestFitIndexReturn\":-0.57378,\"categoryReturn\":-0.49257,\"categoryDailyReturn\":0.75696,\"primaryIndexReturn\":1.10397,\"prospectusPrimaryIndexReturns\":null},{\"period\":\"3M\",\"totalReturn\":-0.85207,\"totalDailyReturn\":3.93777,\"bestFitIndexReturn\":-0.75852,\"categoryReturn\":0.02412,\"categoryDailyReturn\":2.39294,\"primaryIndexReturn\":8.15191,\"prospectusPrimaryIndexReturns\":null},{\"period\":\"6M\",\"totalReturn\":-14.08942,\"totalDailyReturn\":-13.21291,\"bestFitIndexReturn\":-0.12653,\"categoryReturn\":-7.75484,\"categoryDailyReturn\":-2.69177,\"primaryIndexReturn\":5.38014,\"prospectusPrimaryIndexReturns\":null},{\"period\":\"1Y\",\"totalReturn\":-21.45134,\"totalDailyReturn\":-12.68123,\"bestFitIndexReturn\":-0.78449,\"categoryReturn\":-9.45865,\"categoryDailyReturn\":2.48424,\"primaryIndexReturn\":11.26632,\"prospectusPrimaryIndexReturns\":null},{\"period\":\"3Y\",\"totalReturn\":-7.03042,\"totalDailyReturn\":-6.00496,\"bestFitIndexReturn\":-2.30846,\"categoryReturn\":-1.12287,\"categoryDailyReturn\":1.57868,\"primaryIndexReturn\":10.62327,\"prospectusPrimaryIndexReturns\":null},{\"period\":\"5Y\",\"totalReturn\":-0.66910,\"totalDailyReturn\":-0.01870,\"bestFitIndexReturn\":-3.60965,\"categoryReturn\":1.65429,\"categoryDailyReturn\":4.02092,\"primaryIndexReturn\":8.42938,\"prospectusPrimaryIndexReturns\":null},{\"period\":\"10Y\",\"totalReturn\":0.11048,\"totalDailyReturn\":0.22014,\"bestFitIndexReturn\":-0.92211,\"categoryReturn\":1.05914,\"categoryDailyReturn\":1.78486,\"primaryIndexReturn\":7.96920,\"prospectusPrimaryIndexReturns\":null}],\"bestFitIndex\":\"Morningstar US Mod Tgt Alloc NR USD\",\"lastUpdatedDate\":\"2025-07-31\",\"dailyLastUpdatedDate\":\"2025-08-11\"},\"holdingDetails\":{\"totalNetAssets\":\"35497422.24\",\"totalNetAssetsCurrencyCode\":\"USD\",\"annualPortfolioTurnover\":null,\"equityStyle\":null,\"fixedIncomeStyle\":null,\"sharesOutstanding\":830154.87000,\"netAssetValue\":42.76000,\"netAssetValueCurrencyCode\":null,\"premiumDiscountToNAV\":null,\"priceEarningsRatio\":null,\"dividendYield\":0,\"dividendPerShare\":null,\"dividendPerShareCurrency\":\"USD\",\"dividendPerShareCurrencyCode\":\"US Dollar\",\"exDividendDate\":null,\"dividendPaymentDate\":null,\"beta\":-0.51,\"taxAdjustedRating\":null,\"lastUpdatedDate\":\"2025-07-31\"},\"toNewInvestors\":{\"minInitInvst\":50000,\"minInitInvstCurrencyCode\":\"USD\",\"minSubqInvst\":10000,\"minSubqInvstCurrencyCode\":\"USD\",\"minInitRRSPInvst\":0,\"minInitRRSPInvstCurrencyCode\":\"USD\",\"minSubqRRSPInvst\":0,\"minSubqRRSPInvstCurrencyCode\":\"USD\",\"hsbcMinInitInvst\":20000,\"hsbcMinInitInvstCurrencyCode\":\"USD\",\"hsbcMinSubqInvst\":20000,\"hsbcMinSubqInvstCurrencyCode\":\"USD\",\"purchaseCurId\":\"USD\",\"minInitUnit\":\"Monetary\",\"minSubqUnit\":\"Monetary\",\"indicator\":true},\"feesAndExpenses\":{\"maximumInitialSalesFees\":0,\"maximumDeferredSalesFees\":null,\"actualManagementFee\":3.00000,\"prospectusCustodianUnit\":null,\"prospectusCustodianFee\":null,\"actualMER\":null,\"loadType\":null,\"lastUpdatedDate\":null,\"onGoingChargeFigure\":null,\"actualFrontLoad\":null},\"morningstarRatings\":{\"morningstarRatingOverall\":\"2\",\"morningstarRating3Yr\":2,\"morningstarRating5Yr\":2,\"morningstarRating10Yr\":2,\"morningstarTaxAdjustedRatingOverall\":null,\"morningstarTaxAdjustedRating3Yr\":null,\"morningstarTaxAdjustedRating5Yr\":null,\"morningstarTaxAdjustedRating10Yr\":null,\"lastUpdatedDate\":\"2025-07-31\"},\"mgmtAndContactInfo\":{\"companyName\":\"BNY Mellon Fund Services (Ireland) Designated Activity Company\",\"address\":null,\"city\":null,\"province\":null,\"country\":null,\"postalCode\":null,\"telephoneNo\":\"+44 (0) 20 7144 100\",\"faxNo\":null,\"website\":\"https://www.man.com/\",\"mgmtInfos\":[{\"managerName\":\"Russell Korgaonkar\",\"startDate\":\"2021-01-01\"},{\"managerName\":\"Otto Hamaoui\",\"startDate\":\"2022-01-01\"}]},\"investmentStrategy\":{\"investmentStyle\":null,\"interestRateSensitivity\":null,\"assetAllocBondNet\":null,\"preferredStockNet\":null,\"assetAllocCashNet\":null,\"otherNet\":null,\"assetAllocEquityNet\":null},\"yieldAndCredit\":{\"averageCurrentYield\":null,\"averageYieldToMaturity\":null,\"averageDuration\":null,\"lastUpdatedDate\":null,\"creditQualA\":null,\"creditQualAA\":null,\"creditQualAAA\":null,\"creditQualB\":null,\"creditQualBB\":null,\"creditQualBBB\":null,\"creditQualBelowB\":null,\"creditQualNotRated\":null,\"creditQualDate\":null},\"rating\":{\"averageCreditQualityName\":null,\"averageCreditQuality\":null,\"averageCreditQualityDate\":null,\"rank1Yr\":4,\"rank3Yr\":4,\"rank5Yr\":4,\"rank10Yr\":4,\"ratingDate\":null},\"risk\":[{\"yearRisk\":{\"year\":1,\"beta\":0.46,\"stdDev\":15.499,\"alpha\":-30.29,\"sharpeRatio\":-1.761,\"rSquared\":5.14,\"totalReturn\":-21.45134,\"endDate\":\"2025-07-31\"}},{\"yearRisk\":{\"year\":3,\"beta\":-0.51,\"stdDev\":16.864,\"alpha\":-7.76,\"sharpeRatio\":-0.636,\"rSquared\":10.12,\"totalReturn\":-7.03042,\"endDate\":\"2025-07-31\"}},{\"yearRisk\":{\"year\":5,\"beta\":-0.22,\"stdDev\":15.831,\"alpha\":-1.23,\"sharpeRatio\":-0.155,\"rSquared\":2.25,\"totalReturn\":-0.6691,\"endDate\":\"2025-07-31\"}},{\"yearRisk\":{\"year\":10,\"beta\":-0.23,\"stdDev\":14.568,\"alpha\":0.45,\"sharpeRatio\":-0.064,\"rSquared\":2.43,\"totalReturn\":0.11048,\"endDate\":\"2025-07-31\"}}],\"prodAltNumSegs\":[{\"prodCdeAltClassCde\":\"P\",\"prodAltNum\":\"U62345\"},{\"prodCdeAltClassCde\":\"F\",\"prodAltNum\":\"MA345\"},{\"prodCdeAltClassCde\":\"M\",\"prodAltNum\":\"U62345\"},{\"prodCdeAltClassCde\":\"I\",\"prodAltNum\":\"BMG5777T1099\"},{\"prodCdeAltClassCde\":\"O\",\"prodAltNum\":\"0P0000121I\"},{\"prodCdeAltClassCde\":\"T\",\"prodAltNum\":\"000000000000000000001000048143\"},{\"prodCdeAltClassCde\":\"W\",\"prodAltNum\":\"1000048143\"}],\"profile\":{\"name\":\"Man AHL Diversified Futures Ltd.\",\"bestFitIndex\":\"Morningstar US Mod Tgt Alloc NR USD\",\"bestFitIndexCode\":\"F000015CBZ\",\"categoryCode\":\"EUCA001012\",\"categoryName\":\"Systematic Trend USD\",\"categoryLevel1Code\":\"ALTS\",\"categoryLevel1Name\":\"Alternatives\",\"familyName\":\"Man Investments\",\"familyCode\":\"MAN\",\"advisor\":\"BNY Mellon Fund Services (Ireland) Designated Activity Company\",\"subAdvisor\":null,\"inceptionDate\":\"1998-05-12\",\"investmentObjectiveAndStrategy\":\"The Company seeks to achieve substantial medium-term capital growth while aiming to restrict the associated risk. The underlying investment programme, the AHL Diversified Programme, seeks to capitalise primarily on upward and downward price trends in a diversified range of global stock index, bond, currency, short-term interest rate and commodity futures markets. The Company primarily invests in futures and options. The Company also intends to invest extensively in other financial derivative instruments (‘FDI(s)’) to achieve its investment objective, including but not limited to warrants, forward contracts, convertible securities, interest rate swaps, credit default swaps and equity swaps.\",\"hsbcCategoryCode\":\"HG\",\"hsbcCategoryName\":\"Alternatives\",\"dividendYield\":0,\"distributionFrequency\":null,\"riskLvlCde\":\"3\",\"currency\":\"USD\",\"expenseRatio\":null,\"marginRatio\":null,\"initialCharge\":3,\"annualManagementFee\":3,\"assetsUnderManagement\":75125189,\"assetsUnderManagementCurrencyCode\":\"USD\",\"topPerformersIndicator\":null,\"topSellProdIndex\":\"N\",\"investmentRegionCode\":\"GL\",\"investmentRegionName\":\"Global\",\"channelRestrictList\":[\"CMBPWS\",\"SI_I\",\"PIB\",\"IVRS\"],\"fundClassCde\":\"WIC\",\"amcmIndicator\":\"Y\",\"nextDealDate\":\"2025-08-14\",\"surveyedFundNetAssetsDate\":\"2025-08-11\",\"riskFreeRateName\":\"USTREAS T-Bill Auction Ave 3 Mon\",\"relativeRiskMeasuresIndexName\":\"Morningstar US Mod Tgt Alloc NR USD\",\"dayEndBidOfferPricesDate\":null,\"dayEndNAVDate\":\"2025-08-11\",\"prodStatCde\":\"C\",\"allowBuy\":\"N\",\"allowSell\":\"Y\",\"allowSwInProdInd\":\"N\",\"allowSwOutProdInd\":\"Y\",\"allowSellMipProdInd\":\"N\",\"annualReportDate\":\"2016-09-30\",\"piFundInd\":null,\"deAuthFundInd\":null,\"weekRangeLowDate\":\"2025-05-14\",\"weekRangeHighDate\":\"2024-09-26\"}}}",
      "ok": true,
      "from_service_worker": false
    }
  ]
}