{
  "api_name": "wmds_holdingAllocation",
  "product_code": "U62720",
  "timestamp": "20250813_212612",
  "total_responses": 1,
  "responses": [
    {
      "timestamp": "2025-08-13T21:59:17.308893",
      "url": "https://investments3.personal-banking.hsbc.com.hk/shp/wealth-mobile-mds-shp-api-hk-hbap-prod-proxy/v0/wmds/holdingAllocation?body=%7B%22market%22%3A%22HK%22%2C%22productType%22%3A%22UT%22%2C%22prodAltNum%22%3A%22U62720%22%2C%22prodCdeAltClassCde%22%3A%22M%22%7D",
      "status": 200,
      "status_text": "",
      "headers": {
        "x-request-id": "b5149dd4-ad41-4804-a576-ad5de518305d:-:-:-",
        "access-control-expose-headers": "x-authtoken",
        "ratelimit-remaining": "19",
        "content-encoding": "gzip",
        "ratelimit-reset": "1",
        "x-content-type-options": "nosniff",
        "x-ratelimit-limit-second": "20",
        "expires": "0",
        "x-cache": "Miss from cloudfront",
        "x-amz-cf-id": "uQH_J-ADBDH0oh-u2B31R9zqYjH8mgaN_lKVICVHRv1KQmUb-yOdtw==",
        "x-hsbc-request-correlation-id": "6c9279b8-1520-4324-8a6b-3cfb30442ef7",
        "date": "Wed, 13 Aug 2025 13:59:16 GMT",
        "content-type": "application/json;charset=UTF-8",
        "vary": "Accept-Encoding",
        "x-frame-options": "SAMEORIGIN, DENY",
        "strict-transport-security": "max-age=31536000; includeSubDomains",
        "content-security-policy": "default-src 'self';",
        "cache-control": "no-cache, no-store, max-age=0, must-revalidate, no-store, no-cache, must-revalidate",
        "s": "rproxy_prod_tko_0257",
        "pragma": "no-cache, no-cache",
        "x-ratelimit-remaining-second": "19",
        "x-envoy-upstream-service-time": "23",
        "ratelimit-limit": "20",
        "referrer-policy": "no-referrer",
        "via": "1.1 2e4090c5117f92dd57a3a8b0cbf9daa4.cloudfront.net (CloudFront)",
        "access-control-allow-credentials": "true",
        "content-length": "520",
        "x-xss-protection": "1 ; mode=block",
        "x-amz-cf-pop": "LAX54-P4"
      },
      "content_type": "application/json;charset=UTF-8",
      "response_body": "{\"holdingAllocation\":[{\"methods\":\"assetAllocations\",\"breakdowns\":[{\"name\":\"Bond\",\"weighting\":0},{\"name\":\"Cash\",\"weighting\":0},{\"name\":\"Others\",\"weighting\":0},{\"name\":\"Preferred\",\"weighting\":0},{\"name\":\"Stock\",\"weighting\":100}],\"portfolioDate\":\"2025-07-31\"},{\"methods\":\"globalStockSectors\",\"breakdowns\":[{\"name\":\"BM\",\"weighting\":1.11627},{\"name\":\"CC\",\"weighting\":14.50909},{\"name\":\"CD\",\"weighting\":4.7477},{\"name\":\"CS\",\"weighting\":18.56876},{\"name\":\"ENER\",\"weighting\":0},{\"name\":\"FS\",\"weighting\":7.04875},{\"name\":\"HC\",\"weighting\":11.75291},{\"name\":\"INDUS\",\"weighting\":5.50769},{\"name\":\"RE\",\"weighting\":0},{\"name\":\"TECH\",\"weighting\":36.74544},{\"name\":\"UTIL\",\"weighting\":0}],\"portfolioDate\":\"2025-07-31\"},{\"methods\":\"regionalExposures\",\"breakdowns\":[{\"name\":\"AD\",\"weighting\":1.50469},{\"name\":\"AE\",\"weighting\":0},{\"name\":\"AFRICA\",\"weighting\":0},{\"name\":\"AU\",\"weighting\":0},{\"name\":\"CA\",\"weighting\":0.50114},{\"name\":\"EMER\",\"weighting\":0},{\"name\":\"EURO\",\"weighting\":0.29687},{\"name\":\"EZ\",\"weighting\":0.3071},{\"name\":\"JP\",\"weighting\":0},{\"name\":\"LA\",\"weighting\":0},{\"name\":\"ME\",\"weighting\":0},{\"name\":\"NC\",\"weighting\":0},{\"name\":\"UK\",\"weighting\":0},{\"name\":\"US\",\"weighting\":97.38681}],\"portfolioDate\":\"2025-06-30\"},{\"methods\":\"globalBondSectors\",\"breakdowns\":[{\"name\":\"CEQV\",\"weighting\":null},{\"name\":\"CORP\",\"weighting\":null},{\"name\":\"DRVT\",\"weighting\":null},{\"name\":\"GVT\",\"weighting\":null},{\"name\":\"MNCPL\",\"weighting\":null},{\"name\":\"SECZ\",\"weighting\":null}],\"portfolioDate\":\"2025-07-31\"},{\"methods\":\"bondRegionalExposures\",\"breakdowns\":[{\"name\":\"AD\",\"weighting\":null},{\"name\":\"AE\",\"weighting\":null},{\"name\":\"AFRICA\",\"weighting\":null},{\"name\":\"AU\",\"weighting\":null},{\"name\":\"CA\",\"weighting\":null},{\"name\":\"EMER\",\"weighting\":null},{\"name\":\"EURO\",\"weighting\":null},{\"name\":\"EZ\",\"weighting\":null},{\"name\":\"JP\",\"weighting\":null},{\"name\":\"LA\",\"weighting\":null},{\"name\":\"ME\",\"weighting\":null},{\"name\":\"NC\",\"weighting\":null},{\"name\":\"UK\",\"weighting\":null},{\"name\":\"US\",\"weighting\":null}],\"portfolioDate\":\"2025-07-31\"}],\"numberOfStockHoldings\":56,\"numberOfBondHoldings\":0,\"lastUpdatedDate\":\"2025-07-31\"}",
      "ok": true,
      "from_service_worker": false
    }
  ]
}