{
  "api_name": "wmds_holdingAllocation",
  "product_code": "U61110",
  "timestamp": "20250813_212612",
  "total_responses": 1,
  "responses": [
    {
      "timestamp": "2025-08-13T22:04:42.548248",
      "url": "https://investments3.personal-banking.hsbc.com.hk/shp/wealth-mobile-mds-shp-api-hk-hbap-prod-proxy/v0/wmds/holdingAllocation?body=%7B%22market%22%3A%22HK%22%2C%22productType%22%3A%22UT%22%2C%22prodAltNum%22%3A%22U61110%22%2C%22prodCdeAltClassCde%22%3A%22M%22%7D",
      "status": 200,
      "status_text": "",
      "headers": {
        "x-request-id": "b2e17d24-0b95-410c-be53-dd45cf3b84a7:-:-:-",
        "access-control-expose-headers": "x-authtoken",
        "ratelimit-remaining": "19",
        "content-encoding": "gzip",
        "ratelimit-reset": "1",
        "x-content-type-options": "nosniff",
        "x-ratelimit-limit-second": "20",
        "expires": "0",
        "x-cache": "Miss from cloudfront",
        "x-amz-cf-id": "z2eoydUGz7Trg4gF5-_UG2Ykd-nxWNwZIcx5syPxQVAlgbSeVX0CGA==",
        "x-hsbc-request-correlation-id": "a976d97c-d527-44b4-93d1-f7d7b58545fb",
        "date": "Wed, 13 Aug 2025 14:04:42 GMT",
        "content-type": "application/json;charset=UTF-8",
        "vary": "Accept-Encoding",
        "x-frame-options": "SAMEORIGIN, DENY",
        "strict-transport-security": "max-age=31536000; includeSubDomains, max-age=31536000 ; includeSubDomains, max-age=31536000",
        "content-security-policy": "default-src 'self';",
        "cache-control": "no-cache, no-store, max-age=0, must-revalidate, no-store, no-cache, must-revalidate",
        "s": "rproxy_hkp1vl0433",
        "pragma": "no-cache, no-cache",
        "x-ratelimit-remaining-second": "19",
        "x-envoy-upstream-service-time": "17",
        "ratelimit-limit": "20",
        "referrer-policy": "no-referrer",
        "via": "1.1 fbd92e37686376c632f471bbca198756.cloudfront.net (CloudFront)",
        "access-control-allow-credentials": "true",
        "content-length": "527",
        "x-xss-protection": "1 ; mode=block",
        "x-amz-cf-pop": "SYD3-P1"
      },
      "content_type": "application/json;charset=UTF-8",
      "response_body": "{\"holdingAllocation\":[{\"methods\":\"assetAllocations\",\"breakdowns\":[{\"name\":\"Bond\",\"weighting\":82.83547},{\"name\":\"Cash\",\"weighting\":17.10019},{\"name\":\"Others\",\"weighting\":0.0036},{\"name\":\"Preferred\",\"weighting\":0},{\"name\":\"Stock\",\"weighting\":0}],\"portfolioDate\":\"2025-06-30\"},{\"methods\":\"globalStockSectors\",\"breakdowns\":[{\"name\":\"BM\",\"weighting\":0},{\"name\":\"CC\",\"weighting\":0},{\"name\":\"CD\",\"weighting\":0},{\"name\":\"CS\",\"weighting\":0},{\"name\":\"ENER\",\"weighting\":-0.00051},{\"name\":\"FS\",\"weighting\":0},{\"name\":\"HC\",\"weighting\":0},{\"name\":\"INDUS\",\"weighting\":0},{\"name\":\"RE\",\"weighting\":0},{\"name\":\"TECH\",\"weighting\":0},{\"name\":\"UTIL\",\"weighting\":0}],\"portfolioDate\":\"2017-07-31\"},{\"methods\":\"regionalExposures\",\"breakdowns\":[{\"name\":\"AD\",\"weighting\":null},{\"name\":\"AE\",\"weighting\":null},{\"name\":\"AFRICA\",\"weighting\":null},{\"name\":\"AU\",\"weighting\":null},{\"name\":\"CA\",\"weighting\":null},{\"name\":\"EMER\",\"weighting\":null},{\"name\":\"EURO\",\"weighting\":null},{\"name\":\"EZ\",\"weighting\":null},{\"name\":\"JP\",\"weighting\":null},{\"name\":\"LA\",\"weighting\":null},{\"name\":\"ME\",\"weighting\":null},{\"name\":\"NC\",\"weighting\":null},{\"name\":\"UK\",\"weighting\":null},{\"name\":\"US\",\"weighting\":null}],\"portfolioDate\":\"2025-06-30\"},{\"methods\":\"globalBondSectors\",\"breakdowns\":[{\"name\":\"CEQV\",\"weighting\":16.25394},{\"name\":\"CORP\",\"weighting\":15.74634},{\"name\":\"DRVT\",\"weighting\":-8.97219},{\"name\":\"GVT\",\"weighting\":76.96828},{\"name\":\"MNCPL\",\"weighting\":0},{\"name\":\"SECZ\",\"weighting\":0}],\"portfolioDate\":\"2025-06-30\"},{\"methods\":\"bondRegionalExposures\",\"breakdowns\":[{\"name\":\"AD\",\"weighting\":0.11587},{\"name\":\"AE\",\"weighting\":9.78907},{\"name\":\"AFRICA\",\"weighting\":13.87054},{\"name\":\"AU\",\"weighting\":0},{\"name\":\"CA\",\"weighting\":0},{\"name\":\"EMER\",\"weighting\":15.39778},{\"name\":\"EURO\",\"weighting\":0},{\"name\":\"EZ\",\"weighting\":0.12142},{\"name\":\"JP\",\"weighting\":0},{\"name\":\"LA\",\"weighting\":39.26803},{\"name\":\"ME\",\"weighting\":14.14255},{\"name\":\"NC\",\"weighting\":0},{\"name\":\"UK\",\"weighting\":0.06991},{\"name\":\"US\",\"weighting\":0}],\"portfolioDate\":\"2025-06-30\"}],\"numberOfStockHoldings\":0,\"numberOfBondHoldings\":286,\"lastUpdatedDate\":\"2025-06-30\"}",
      "ok": true,
      "from_service_worker": false
    }
  ]
}