{
  "api_name": "wmds_fundQuoteSummary",
  "product_code": "U62519",
  "timestamp": "20250813_212612",
  "total_responses": 1,
  "responses": [
    {
      "timestamp": "2025-08-13T21:48:06.051916",
      "url": "https://investments3.personal-banking.hsbc.com.hk/shp/wealth-mobile-mds-shp-api-hk-hbap-prod-proxy/v0/wmds/fundQuoteSummary?body=%7B%22productType%22%3A%22UT%22%2C%22prodAltNum%22%3A%22U62519%22%2C%22prodCdeAltClassCde%22%3A%22M%22%2C%22market%22%3A%22HK%22%7D",
      "status": 200,
      "status_text": "",
      "headers": {
        "x-request-id": "4701fc8e-468a-4889-bfba-c04f2f56e5b8:-:-:-",
        "access-control-expose-headers": "x-authtoken",
        "ratelimit-remaining": "16",
        "content-encoding": "gzip",
        "ratelimit-reset": "1",
        "x-content-type-options": "nosniff",
        "x-ratelimit-limit-second": "20",
        "expires": "0",
        "x-cache": "Miss from cloudfront",
        "x-amz-cf-id": "-2RnD8QiJqbXcyTfrrB7HvET_95JszQDAtrwXiuW6sw19pPc4ZbQPQ==",
        "x-hsbc-request-correlation-id": "c14f4e40-a798-4127-8871-670198275455",
        "date": "Wed, 13 Aug 2025 13:48:05 GMT",
        "content-type": "application/json;charset=UTF-8",
        "vary": "Accept-Encoding",
        "x-frame-options": "SAMEORIGIN, DENY",
        "strict-transport-security": "max-age=16070400; includeSubDomains; preload",
        "content-security-policy": "default-src 'self';",
        "cache-control": "no-cache, no-store, max-age=0, must-revalidate, no-store, no-cache, must-revalidate",
        "s": "rproxy_prod_skm_0254",
        "pragma": "no-cache, no-cache",
        "x-ratelimit-remaining-second": "16",
        "x-envoy-upstream-service-time": "28",
        "ratelimit-limit": "20",
        "referrer-policy": "no-referrer",
        "via": "1.1 612d6e38ca8a5e65776b064d65f27d36.cloudfront.net (CloudFront)",
        "access-control-allow-credentials": "true",
        "content-length": "3176",
        "x-xss-protection": "1 ; mode=block",
        "x-amz-cf-pop": "SYD3-P1"
      },
      "content_type": "application/json;charset=UTF-8",
      "response_body": "{\"summary\":{\"bid\":null,\"weekRangeLow\":7.41100,\"weekRangeHigh\":7.86600,\"offer\":null,\"weekRangeCurrency\":\"HKD\",\"calendarYearTotalReturns\":{\"items\":[{\"year\":2024,\"fundCalendarYearReturn\":5.94680,\"fundStubYearEndReturn\":null,\"stubYearEndReturnIndicator\":null,\"bestFitIndexCalendarYearReturn\":6.79687,\"categoryCalendarYearReturn\":6.75073,\"prospectusPrimaryIndexYearReturns\":[{\"indexId\":\"F00001GI4V\",\"indexName\":\"ICE BofA BB-B DM HY Constnd H TR USD\",\"weighting\":100,\"prospectusPrimaryIndex\":null}]},{\"year\":2023,\"fundCalendarYearReturn\":10.32089,\"fundStubYearEndReturn\":null,\"stubYearEndReturnIndicator\":null,\"bestFitIndexCalendarYearReturn\":14.33766,\"categoryCalendarYearReturn\":11.48231,\"prospectusPrimaryIndexYearReturns\":[{\"indexId\":\"F00001GI4V\",\"indexName\":\"ICE BofA BB-B DM HY Constnd H TR USD\",\"weighting\":100,\"prospectusPrimaryIndex\":null}]},{\"year\":2022,\"fundCalendarYearReturn\":-13.47532,\"fundStubYearEndReturn\":null,\"stubYearEndReturnIndicator\":null,\"bestFitIndexCalendarYearReturn\":-12.57459,\"categoryCalendarYearReturn\":-11.33721,\"prospectusPrimaryIndexYearReturns\":[{\"indexId\":\"F00001GI4V\",\"indexName\":\"ICE BofA BB-B DM HY Constnd H TR USD\",\"weighting\":100,\"prospectusPrimaryIndex\":null}]},{\"year\":2021,\"fundCalendarYearReturn\":1.76762,\"fundStubYearEndReturn\":null,\"stubYearEndReturnIndicator\":null,\"bestFitIndexCalendarYearReturn\":3.09093,\"categoryCalendarYearReturn\":2.49717,\"prospectusPrimaryIndexYearReturns\":[{\"indexId\":\"F00001GI4V\",\"indexName\":\"ICE BofA BB-B DM HY Constnd H TR USD\",\"weighting\":100,\"prospectusPrimaryIndex\":null}]},{\"year\":2020,\"fundCalendarYearReturn\":5.73967,\"fundStubYearEndReturn\":null,\"stubYearEndReturnIndicator\":null,\"bestFitIndexCalendarYearReturn\":8.03245,\"categoryCalendarYearReturn\":5.19219,\"prospectusPrimaryIndexYearReturns\":[{\"indexId\":\"F00001GI4V\",\"indexName\":\"ICE BofA BB-B DM HY Constnd H TR USD\",\"weighting\":100,\"prospectusPrimaryIndex\":null}]}],\"bestFitIndex\":\"Morningstar Gbl HY Bd GR USD\",\"lastUpdatedDate\":\"2025-07-31\",\"dailyLastUpdatedDate\":\"2025-08-12\"},\"cumulativeTotalReturns\":{\"items\":[{\"period\":\"YTD\",\"totalReturn\":5.74519,\"totalDailyReturn\":6.38229,\"bestFitIndexReturn\":7.12944,\"categoryReturn\":5.57906,\"categoryDailyReturn\":6.04452,\"primaryIndexReturn\":7.12944,\"prospectusPrimaryIndexReturns\":[{\"indexId\":\"F00001GI4V\",\"indexName\":\"ICE BofA BB-B DM HY Constnd H TR USD\",\"weighting\":100,\"prospectusPrimaryIndex\":null}]},{\"period\":\"1M\",\"totalReturn\":0.03955,\"totalDailyReturn\":0.79655,\"bestFitIndexReturn\":-0.02133,\"categoryReturn\":0.33060,\"categoryDailyReturn\":0.89309,\"primaryIndexReturn\":-0.02133,\"prospectusPrimaryIndexReturns\":[{\"indexId\":\"F00001GI4V\",\"indexName\":\"ICE BofA BB-B DM HY Constnd H TR USD\",\"weighting\":100,\"prospectusPrimaryIndex\":null}]},{\"period\":\"3M\",\"totalReturn\":4.42305,\"totalDailyReturn\":3.64603,\"bestFitIndexReturn\":3.86574,\"categoryReturn\":3.70839,\"categoryDailyReturn\":3.68471,\"primaryIndexReturn\":3.86574,\"prospectusPrimaryIndexReturns\":[{\"indexId\":\"F00001GI4V\",\"indexName\":\"ICE BofA BB-B DM HY Constnd H TR USD\",\"weighting\":100,\"prospectusPrimaryIndex\":null}]},{\"period\":\"6M\",\"totalReturn\":4.41414,\"totalDailyReturn\":5.15224,\"bestFitIndexReturn\":5.76649,\"categoryReturn\":4.48091,\"categoryDailyReturn\":4.82074,\"primaryIndexReturn\":5.76649,\"prospectusPrimaryIndexReturns\":[{\"indexId\":\"F00001GI4V\",\"indexName\":\"ICE BofA BB-B DM HY Constnd H TR USD\",\"weighting\":100,\"prospectusPrimaryIndex\":null}]},{\"period\":\"1Y\",\"totalReturn\":7.88723,\"totalDailyReturn\":8.59340,\"bestFitIndexReturn\":9.88799,\"categoryReturn\":8.27973,\"categoryDailyReturn\":8.75717,\"primaryIndexReturn\":9.88799,\"prospectusPrimaryIndexReturns\":[{\"indexId\":\"F00001GI4V\",\"indexName\":\"ICE BofA BB-B DM HY Constnd H TR USD\",\"weighting\":100,\"prospectusPrimaryIndex\":null}]},{\"period\":\"3Y\",\"totalReturn\":6.71019,\"totalDailyReturn\":6.16205,\"bestFitIndexReturn\":8.95334,\"categoryReturn\":7.79035,\"categoryDailyReturn\":7.55913,\"primaryIndexReturn\":8.95334,\"prospectusPrimaryIndexReturns\":[{\"indexId\":\"F00001GI4V\",\"indexName\":\"ICE BofA BB-B DM HY Constnd H TR USD\",\"weighting\":100,\"prospectusPrimaryIndex\":null}]},{\"period\":\"5Y\",\"totalReturn\":2.77800,\"totalDailyReturn\":2.82451,\"bestFitIndexReturn\":4.79554,\"categoryReturn\":4.31683,\"categoryDailyReturn\":4.21406,\"primaryIndexReturn\":4.79554,\"prospectusPrimaryIndexReturns\":[{\"indexId\":\"F00001GI4V\",\"indexName\":\"ICE BofA BB-B DM HY Constnd H TR USD\",\"weighting\":100,\"prospectusPrimaryIndex\":null}]},{\"period\":\"10Y\",\"totalReturn\":3.67274,\"totalDailyReturn\":3.81118,\"bestFitIndexReturn\":5.16220,\"categoryReturn\":3.99719,\"categoryDailyReturn\":4.26042,\"primaryIndexReturn\":5.16220,\"prospectusPrimaryIndexReturns\":[{\"indexId\":\"F00001GI4V\",\"indexName\":\"ICE BofA BB-B DM HY Constnd H TR USD\",\"weighting\":100,\"prospectusPrimaryIndex\":null}]}],\"bestFitIndex\":\"Morningstar Gbl HY Bd GR USD\",\"lastUpdatedDate\":\"2025-07-31\",\"dailyLastUpdatedDate\":\"2025-08-12\"},\"holdingDetails\":{\"totalNetAssets\":\"289580167\",\"totalNetAssetsCurrencyCode\":\"HKD\",\"annualPortfolioTurnover\":null,\"equityStyle\":\"7\",\"fixedIncomeStyle\":\"7\",\"sharesOutstanding\":36900282.74700,\"netAssetValue\":7.84800,\"netAssetValueCurrencyCode\":null,\"premiumDiscountToNAV\":null,\"priceEarningsRatio\":null,\"dividendYield\":6.68758,\"dividendPerShare\":\"0.042214000\",\"dividendPerShareCurrency\":\"HKD\",\"dividendPerShareCurrencyCode\":\"Hong Kong Dollar\",\"exDividendDate\":\"2025-07-30\",\"dividendPaymentDate\":null,\"beta\":0.80,\"taxAdjustedRating\":null,\"lastUpdatedDate\":\"2025-07-31\"},\"toNewInvestors\":{\"minInitInvst\":5000,\"minInitInvstCurrencyCode\":\"HKD\",\"minSubqInvst\":null,\"minSubqInvstCurrencyCode\":\"HKD\",\"minInitRRSPInvst\":0,\"minInitRRSPInvstCurrencyCode\":\"HKD\",\"minSubqRRSPInvst\":0,\"minSubqRRSPInvstCurrencyCode\":\"HKD\",\"hsbcMinInitInvst\":10000,\"hsbcMinInitInvstCurrencyCode\":\"HKD\",\"hsbcMinSubqInvst\":10000,\"hsbcMinSubqInvstCurrencyCode\":\"HKD\",\"purchaseCurId\":\"HKD\",\"minInitUnit\":\"Monetary\",\"minSubqUnit\":null,\"indicator\":true},\"feesAndExpenses\":{\"maximumInitialSalesFees\":3.10000,\"maximumDeferredSalesFees\":0,\"actualManagementFee\":1.10000,\"prospectusCustodianUnit\":null,\"prospectusCustodianFee\":null,\"actualMER\":null,\"loadType\":null,\"lastUpdatedDate\":\"2025-06-13\",\"onGoingChargeFigure\":1.35,\"actualFrontLoad\":null},\"morningstarRatings\":{\"morningstarRatingOverall\":\"2\",\"morningstarRating3Yr\":2,\"morningstarRating5Yr\":2,\"morningstarRating10Yr\":2,\"morningstarTaxAdjustedRatingOverall\":null,\"morningstarTaxAdjustedRating3Yr\":null,\"morningstarTaxAdjustedRating5Yr\":null,\"morningstarTaxAdjustedRating10Yr\":null,\"lastUpdatedDate\":\"2025-07-31\"},\"mgmtAndContactInfo\":{\"companyName\":\"HSBC Continental Europe, Luxembourg\",\"address\":\"C/O HSBC Securities Services (Luxembourg) S.A.,16, BOULEVARD D'AVRANCHES,LUXEMBOURG\",\"city\":\"Luxembourg\",\"province\":null,\"country\":null,\"postalCode\":\"L-1160\",\"telephoneNo\":\"(+352) 40 46 46 767\",\"faxNo\":\"(+352) 48 88 96 31\",\"website\":\"http://www.assetmanagement.hsbc.com\",\"mgmtInfos\":[{\"managerName\":\"Ricky Liu\",\"startDate\":\"2025-05-01\"}]},\"investmentStrategy\":{\"investmentStyle\":\"7\",\"interestRateSensitivity\":\"7\",\"assetAllocBondNet\":97.32467,\"preferredStockNet\":0.47492,\"assetAllocCashNet\":1.23836,\"otherNet\":0.37275,\"assetAllocEquityNet\":0},\"yieldAndCredit\":{\"averageCurrentYield\":6.74011,\"averageYieldToMaturity\":6.30977,\"averageDuration\":2.72008,\"lastUpdatedDate\":\"2025-06-30\",\"creditQualA\":0,\"creditQualAA\":0,\"creditQualAAA\":0,\"creditQualB\":33.07462,\"creditQualBB\":58.23856,\"creditQualBBB\":2.64676,\"creditQualBelowB\":2.72949,\"creditQualNotRated\":3.31054,\"creditQualDate\":\"2025-06-30\"},\"rating\":{\"averageCreditQualityName\":\"BB\",\"averageCreditQuality\":14,\"averageCreditQualityDate\":\"2025-06-30\",\"rank1Yr\":3,\"rank3Yr\":4,\"rank5Yr\":4,\"rank10Yr\":3,\"ratingDate\":\"2025-06-30\"},\"risk\":[{\"yearRisk\":{\"year\":1,\"beta\":0.71,\"stdDev\":2.899,\"alpha\":-0.91,\"sharpeRatio\":0.914,\"rSquared\":82.94,\"totalReturn\":7.88723,\"endDate\":\"2025-07-31\"}},{\"yearRisk\":{\"year\":3,\"beta\":0.8,\"stdDev\":5.564,\"alpha\":-1.36,\"sharpeRatio\":0.33,\"rSquared\":93.46,\"totalReturn\":6.71019,\"endDate\":\"2025-07-31\"}},{\"yearRisk\":{\"year\":5,\"beta\":0.82,\"stdDev\":6.63,\"alpha\":-1.94,\"sharpeRatio\":-0.051,\"rSquared\":93.2,\"totalReturn\":2.778,\"endDate\":\"2025-07-31\"}},{\"yearRisk\":{\"year\":10,\"beta\":0.88,\"stdDev\":7.302,\"alpha\":-1.21,\"sharpeRatio\":0.228,\"rSquared\":94.87,\"totalReturn\":3.67274,\"endDate\":\"2025-07-31\"}}],\"prodAltNumSegs\":[{\"prodCdeAltClassCde\":\"P\",\"prodAltNum\":\"U62519\"},{\"prodCdeAltClassCde\":\"F\",\"prodAltNum\":\"HGYHK\"},{\"prodCdeAltClassCde\":\"M\",\"prodAltNum\":\"U62519\"},{\"prodCdeAltClassCde\":\"I\",\"prodAltNum\":\"LU0780247127\"},{\"prodCdeAltClassCde\":\"O\",\"prodAltNum\":\"0P0000WL9Q\"},{\"prodCdeAltClassCde\":\"T\",\"prodAltNum\":\"000000000000000000001000047655\"},{\"prodCdeAltClassCde\":\"W\",\"prodAltNum\":\"1000047655\"}],\"profile\":{\"name\":\"HSBC GIF - GLOBAL HIGH YIELD BOND FUND (CLASS AM2-HKD-MDIST-CASH)\",\"bestFitIndex\":\"Morningstar Gbl HY Bd GR USD\",\"bestFitIndexCode\":\"F000011PG3\",\"categoryCode\":\"EUCA000766\",\"categoryName\":\"Global High Yield Bond\",\"categoryLevel1Code\":\"FI\",\"categoryLevel1Name\":\"Fixed Income\",\"familyName\":\"HSBC Global Asset Management  (Hong Kong) Limited\",\"familyCode\":\"HSBCA\",\"advisor\":\"HSBC Continental Europe, Luxembourg\",\"subAdvisor\":\"HSBC Global Asset Management (France)\",\"inceptionDate\":\"2012-07-20\",\"investmentObjectiveAndStrategy\":\"The sub-fund invests for total return primarily in a diversified portfolio of Non-Investment Grade and unrated fixed income securities either issued by companies or issued or guaranteed by governments, government agencies, quasi-government entities, state sponsored enterprises, local or regional governments (including state, provincial, and municipal governments and governmental entities) and supranational bodies and denominated in or hedged into United States Dollars (USD). Under normal market conditions, a minimum of 90% of the sub-fund’s net assets will be invested in Non-Investment Grade rated and other higher yielding bonds (including unrated bonds). However, for liquidity management purposes, the sub-fund may at times invest up to 30% in Investment Grade rated fixed income securities.\",\"hsbcCategoryCode\":\"HL\",\"hsbcCategoryName\":\"High Yield Bond - Global\",\"dividendYield\":6.68758,\"distributionFrequency\":\"Monthly\",\"riskLvlCde\":\"4\",\"currency\":\"HKD\",\"expenseRatio\":null,\"marginRatio\":null,\"initialCharge\":2,\"annualManagementFee\":1.1,\"assetsUnderManagement\":900797137,\"assetsUnderManagementCurrencyCode\":\"USD\",\"topPerformersIndicator\":null,\"topSellProdIndex\":\"N\",\"investmentRegionCode\":\"GL\",\"investmentRegionName\":\"Global\",\"channelRestrictList\":[\"SI_I\"],\"fundClassCde\":\"WIC\",\"amcmIndicator\":\"Y\",\"nextDealDate\":\"2025-08-13\",\"surveyedFundNetAssetsDate\":\"2025-08-12\",\"riskFreeRateName\":\"USTREAS T-Bill Auction Ave 3 Mon\",\"relativeRiskMeasuresIndexName\":\"Morningstar Gbl HY Bd GR USD\",\"dayEndBidOfferPricesDate\":null,\"dayEndNAVDate\":\"2025-08-12\",\"prodStatCde\":\"A\",\"allowBuy\":\"Y\",\"allowSell\":\"Y\",\"allowSwInProdInd\":\"Y\",\"allowSwOutProdInd\":\"Y\",\"allowSellMipProdInd\":\"Y\",\"annualReportDate\":\"2025-03-31\",\"piFundInd\":null,\"deAuthFundInd\":null,\"weekRangeLowDate\":\"2025-04-09\",\"weekRangeHighDate\":\"2025-07-28\"}}}",
      "ok": true,
      "from_service_worker": false
    }
  ]
}