{
  "api_name": "wmds_quoteDetail",
  "product_code": "U63277",
  "timestamp": "20250813_212612",
  "total_responses": 1,
  "responses": [
    {
      "timestamp": "2025-08-13T21:27:18.583053",
      "url": "https://investments3.personal-banking.hsbc.com.hk/shp/wealth-mobile-mds-shp-api-hk-hbap-prod-proxy/v0/wmds/quoteDetail?body=%7B%22market%22%3A%22HK%22%2C%22productType%22%3A%22UT%22%2C%22prodAltNum%22%3A%22U63277%22%2C%22prodCdeAltClassCde%22%3A%22M%22%2C%22delay%22%3Atrue%2C%22entityTimezone%22%3A%22Asia%2FHong_Kong%22%7D",
      "status": 200,
      "status_text": "",
      "headers": {
        "x-request-id": "20132947-1425-46d2-8d23-9762e100b774:-:-:-",
        "access-control-expose-headers": "x-authtoken",
        "ratelimit-remaining": "17",
        "content-encoding": "gzip",
        "ratelimit-reset": "1",
        "x-content-type-options": "nosniff",
        "x-ratelimit-limit-second": "20",
        "expires": "0",
        "x-cache": "Miss from cloudfront",
        "x-amz-cf-id": "530P3duoWzl9VbABQb_cbPQQNDjM72tsHs20fCfaenyn9V1FaE67Bg==",
        "x-hsbc-request-correlation-id": "d9533d6a-aaf6-450a-9136-c6f501625c08",
        "date": "Wed, 13 Aug 2025 13:27:17 GMT",
        "content-type": "application/json;charset=UTF-8",
        "vary": "Accept-Encoding",
        "x-frame-options": "SAMEORIGIN, DENY",
        "strict-transport-security": "max-age=31536000; includeSubDomains, max-age=31536000 ; includeSubDomains, max-age=31536000",
        "content-security-policy": "default-src 'self';",
        "cache-control": "no-cache, no-store, max-age=0, must-revalidate, no-store, no-cache, must-revalidate",
        "s": "rproxy_hkp1vl0430",
        "pragma": "no-cache, no-cache",
        "x-ratelimit-remaining-second": "17",
        "x-envoy-upstream-service-time": "20",
        "ratelimit-limit": "20",
        "referrer-policy": "no-referrer",
        "via": "1.1 db2c2df01e7441e6c4555e1d92668506.cloudfront.net (CloudFront)",
        "access-control-allow-credentials": "true",
        "content-length": "1230",
        "x-xss-protection": "1 ; mode=block",
        "x-amz-cf-pop": "SEA900-P4"
      },
      "content_type": "application/json;charset=UTF-8",
      "response_body": "{\"requestType\":null,\"remainingQuote\":null,\"totalQuote\":null,\"indexQuotes\":null,\"bidAskQuotes\":null,\"priceQuote\":{\"productStatus\":null,\"ric\":null,\"symbol\":\"U63277\",\"market\":\"HK\",\"productType\":\"UT\",\"productSubTypeCode\":\"SS\",\"prodCdeAltClassCde\":null,\"quoteIndicator\":true,\"priceQuote\":12.317,\"currency\":\"HKD\",\"companyName\":\"HSBC GIF - GLOBAL INFRASTRUCTURE EQUITY (CLASS AM2-HKD-MD-CASH)\",\"securityDescription\":null,\"changeAmount\":0.008,\"changePercent\":0.06499,\"bidPrice\":null,\"bidPriceDate\":null,\"bidSize\":null,\"askPrice\":null,\"askSize\":null,\"dayRangeLow\":null,\"dayRangeHigh\":null,\"tradingVolume\":null,\"openPrice\":null,\"yearLowPrice\":null,\"yearHighPrice\":null,\"averageVolume\":null,\"peRatio\":null,\"marketCap\":null,\"sharesOutstanding\":null,\"beta\":null,\"previousClosePrice\":null,\"dividend\":null,\"dividendYield\":3.74321,\"exDividendDate\":null,\"boardLot\":null,\"casEligibleFlag\":null,\"status\":null,\"historyCloseDate\":null,\"turnOver\":null,\"marketClosed\":null,\"nominalPriceType\":null,\"spreadBid\":null,\"spreadAsk\":null,\"eps\":null,\"iep\":null,\"iev\":null,\"turnoverAmount\":null,\"turnoverIncludeAmount\":null,\"quoteSector\":null,\"quoteIndustry\":null,\"quoteExchange\":null,\"quote1MPercChange\":null,\"quote3MPercChange\":null,\"quote6MPercChange\":null,\"quote12MPercChange\":null,\"exchangeTimezone\":null,\"exchangeUpdatedTime\":\"2025-08-12\",\"unsignedAgreementId\":null,\"quoteVMA50D\":null,\"prodShoreLocCde\":null,\"allowSellMipProdInd\":\"Y\",\"upperTradingLimit\":null,\"lowerTradingLimit\":null,\"riskAlert\":null,\"riskRating\":null,\"riskLvlCde\":\"5\",\"option\":null,\"bond\":null,\"interestRate\":null,\"commodity\":null,\"performanceId\":\"0P0001Q9E0\",\"tradableCurrency\":\"HKD\",\"agreementSignStatus\":null,\"agreementId\":null,\"inDaylightTime\":null,\"tradeUnits\":null,\"distributionFrequency\":\"Monthly\",\"topPerformersIndicator\":null,\"topSellProdIndex\":\"N\",\"categoryLevel1Code\":\"SPEC\",\"categoryLevel1Name\":\"Specialties\",\"allowBuy\":\"Y\",\"allowSell\":\"Y\",\"piFundInd\":\"N\",\"deAuthFundInd\":\"N\",\"calendarReturns\":{\"items\":[{\"year\":2024,\"annualCalendarYearReturn\":9.03309},{\"year\":2023,\"annualCalendarYearReturn\":8.06756},{\"year\":2022,\"annualCalendarYearReturn\":null},{\"year\":2021,\"annualCalendarYearReturn\":null},{\"year\":2020,\"annualCalendarYearReturn\":null}],\"monthEndDate\":\"2025-07-31\"},\"cumulativeReturns\":{\"items\":[{\"period\":\"YTD\",\"trailingTotalReturn\":12.20311,\"dailyPerformanceNAV\":13.9047},{\"period\":\"1M\",\"trailingTotalReturn\":-1.03416,\"dailyPerformanceNAV\":1.53162},{\"period\":\"3M\",\"trailingTotalReturn\":3.57305,\"dailyPerformanceNAV\":6.11258},{\"period\":\"6M\",\"trailingTotalReturn\":11.19327,\"dailyPerformanceNAV\":12.83897},{\"period\":\"1Y\",\"trailingTotalReturn\":12.26913,\"dailyPerformanceNAV\":14.13424},{\"period\":\"3Y\",\"trailingTotalReturn\":null,\"dailyPerformanceNAV\":null},{\"period\":\"5Y\",\"trailingTotalReturn\":null,\"dailyPerformanceNAV\":null},{\"period\":\"10Y\",\"trailingTotalReturn\":null,\"dailyPerformanceNAV\":null}],\"monthEndDate\":\"2025-07-31\",\"dayEndDate\":\"2025-08-12\"},\"launchDate\":\"2023-02-13\"},\"entityUpdatedTime\":\"2025-08-13T21:27:17.000+08:00\",\"prodAltNumSegs\":[{\"prodCdeAltClassCde\":\"P\",\"prodAltNum\":\"U63277\"},{\"prodCdeAltClassCde\":\"F\",\"prodAltNum\":\"GIEMH\"},{\"prodCdeAltClassCde\":\"M\",\"prodAltNum\":\"U63277\"},{\"prodCdeAltClassCde\":\"I\",\"prodAltNum\":\"LU2545637220\"},{\"prodCdeAltClassCde\":\"O\",\"prodAltNum\":\"0P0001Q9E0\"},{\"prodCdeAltClassCde\":\"T\",\"prodAltNum\":\"000000000000000000000050637676\"},{\"prodCdeAltClassCde\":\"W\",\"prodAltNum\":\"50637676\"}]}",
      "ok": true,
      "from_service_worker": false
    }
  ]
}